odoo/addons/stock_procurement_group_hook/README.rst
odoo/addons/stock_procurement_group_hook/__init__.py
odoo/addons/stock_procurement_group_hook/__manifest__.py
odoo/addons/stock_procurement_group_hook/hooks.py
odoo/addons/stock_procurement_group_hook/i18n/it.po
odoo/addons/stock_procurement_group_hook/i18n/stock_procurement_group_hook.pot
odoo/addons/stock_procurement_group_hook/models/__init__.py
odoo/addons/stock_procurement_group_hook/models/procurement_group.py
odoo/addons/stock_procurement_group_hook/readme/CONTRIBUTORS.rst
odoo/addons/stock_procurement_group_hook/readme/DESCRIPTION.rst
odoo/addons/stock_procurement_group_hook/static/description/icon.png
odoo/addons/stock_procurement_group_hook/static/description/index.html
odoo14_addon_stock_procurement_group_hook-14.0.1.0.1.dev5.dist-info/METADATA
odoo14_addon_stock_procurement_group_hook-14.0.1.0.1.dev5.dist-info/WHEEL
odoo14_addon_stock_procurement_group_hook-14.0.1.0.1.dev5.dist-info/top_level.txt
odoo14_addon_stock_procurement_group_hook-14.0.1.0.1.dev5.dist-info/RECORD
